systemd_unit
